robot_rumble/Player.py
robot_rumble/__init__.py
robot_rumble/boss.py
robot_rumble/constants.py
robot_rumble/driver.py
robot_rumble/main.py
robot_rumble/projectile.py
robot_rumble/Characters/__init__.py
robot_rumble/Characters/crawler.py
robot_rumble/Characters/death.py
robot_rumble/Characters/drone.py
robot_rumble/Characters/entities.py
robot_rumble/Characters/heart.py
robot_rumble/Characters/projectiles.py
robot_rumble/Characters/turret.py
robot_rumble/Characters/Boss/__init__.py
robot_rumble/Characters/Boss/bossBase.py
robot_rumble/Characters/Boss/bossOne.py
robot_rumble/Characters/Boss/bossTwo.py
robot_rumble/Characters/Player/__init__.py
robot_rumble/Characters/Player/playerBase.py
robot_rumble/Characters/Player/playerFighter.py
robot_rumble/Characters/Player/playerGunner.py
robot_rumble/Characters/Player/playerSwordster.py
robot_rumble/Level/__init__.py
robot_rumble/Level/level.py
robot_rumble/Level/levelOne.py
robot_rumble/Level/levelOneBoss.py
robot_rumble/Level/levelTwo.py
robot_rumble/Level/levelTwoBoss.py
robot_rumble/Screens/__init__.py
robot_rumble/Screens/characterSelectScreen.py
robot_rumble/Screens/controlScreen.py
robot_rumble/Screens/deathScreen.py
robot_rumble/Screens/optionsScreen.py
robot_rumble/Screens/pauseScreen.py
robot_rumble/Screens/titleScreen.py
robot_rumble/Screens/winScreen.py
robot_rumble/Util/__init__.py
robot_rumble/Util/collisionHandler.py
robot_rumble/Util/constants.py
robot_rumble/Util/spriteload.py
robot_rumble/assets/.DS_Store
robot_rumble/assets/Boss2_Level.json
robot_rumble/assets/Boss_Level.json
robot_rumble/assets/Platforms.tsx
robot_rumble/assets/Prototype.json
robot_rumble/assets/Robot_idle.png
robot_rumble/assets/Robot_run.png
robot_rumble/assets/black_screen.jpeg
robot_rumble/assets/control_screen.png
robot_rumble/assets/door.png
robot_rumble/assets/gunner_button.png
robot_rumble/assets/health_bar.png
robot_rumble/assets/heart.png
robot_rumble/assets/platform.png
robot_rumble/assets/platform_purple.png
robot_rumble-0.2.0.dist-info/METADATA
robot_rumble-0.2.0.dist-info/WHEEL
robot_rumble-0.2.0.dist-info/entry_points.txt
robot_rumble-0.2.0.dist-info/top_level.txt
robot_rumble-0.2.0.dist-info/RECORD
