Metadata-Version: 2.1
Name: robot-rumble
Version: 0.2.0
Summary: 2D Side-Scroller Game for UF CEN4930 Performant Programming (in Japan!)
Home-page: https://github.com/guptat07/Robot-Rumble
Author: Tony Gupta, Anthony Liao, Maya Singh, Kaylee Conrad
Author-email: kaymconrad@gmail.com
License: UNKNOWN
Platform: UNKNOWN
Requires-Python: ==3.10.*
Requires-Dist: arcade (>=2.6.17)
